reacnet/__init__.py
reacnet/connectors/__init__.py
reacnet/connectors/connection.py
reacnet/elements/__init__.py
reacnet/elements/elementbase.py
reacnet/elements/flowreactor.py
reacnet/elements/mixer.py
reacnet/elements/tank.py
reacnet/networks/network.py
reacnet-0.0.4.dist-info/METADATA
reacnet-0.0.4.dist-info/WHEEL
reacnet-0.0.4.dist-info/top_level.txt
reacnet-0.0.4.dist-info/RECORD
