Metadata-Version: 2.1
Name: reacnet
Version: 0.0.4
Summary: a tool for building reactor network based on omnisoot and Cantera
Author-email: Mo Adib <moademic@gmail.com>
Project-URL: Homepage, https://carleton.ca/eptl/people/336/
Keywords: computational,chemical kinetics,soot
Classifier: Programming Language :: Python :: 3
Requires-Python: >=3.7
